aegis_lang/__init__.py
aegis_lang-0.1.0.data/scripts/aegis
aegis_lang-0.1.0.dist-info/METADATA
aegis_lang-0.1.0.dist-info/WHEEL
aegis_lang-0.1.0.dist-info/licenses/LICENSE
aegis_lang-0.1.0.dist-info/RECORD
