Metadata-Version: 2.4
Name: aegis-lang
Version: 0.1.0
Classifier: Programming Language :: Rust
Classifier: Programming Language :: Python :: Implementation :: CPython
Classifier: Programming Language :: Python :: Implementation :: PyPy
Classifier: Topic :: Software Development :: Compilers
Classifier: Topic :: Software Development :: Interpreters
Classifier: Intended Audience :: Developers
Classifier: License :: OSI Approved :: MIT License
License-File: LICENSE
Summary: Current World's Fastest Agentic AI Language
Author-email: AEGIS Research Team <teerth@example.com>
Requires-Python: >=3.7
